.gitignore
LICENSE
README.md
environment.yml
requirements.txt
setup.py
.github/workflows/python-package.yml
.github/workflows/python-publish.yml
bpc/__init__.py
bpc/version.py
bpc.egg-info/PKG-INFO
bpc.egg-info/SOURCES.txt
bpc.egg-info/dependency_links.txt
bpc.egg-info/requires.txt
bpc.egg-info/top_level.txt
bpc/cleaner/__init__.py
bpc/cleaner/clean.py
bpc/cleaner/converter.py
bpc/cleaner/normalizer.py
bpc/cleaner/preprocessor.py
bpc/cleaner/word_break.py
bpc/dataset/__init__.py
bpc/dataset/dataframe.py
bpc/dataset/prepare_dataset.py
bpc/dataset/train_test_split.py
bpc/phonemizer/__init__.py
bpc/phonemizer/bootphonemizer.py
bpc/phonemizer/phonemize.py
demo/demo.ipynb