Metadata-Version: 2.1
Name: bpc
Version: 0.1.3
Summary: Burmese text normalizer, wordbreak, converter, cleaner and phonemizer for speech related tasks.
Home-page: https://github.com/1chimaruGin/Burmese_Phomizer_and_Cleaner
Author: kyitharhein
Author-email: kyitharhein18@gmail.com
License: UNKNOWN
Download-URL: https://github.com/1chimaruGin/Burmese_Phomizer_and_Cleaner/archive/refs/tags/v0.0.1.tar.gz
Platform: UNKNOWN
Classifier: Development Status :: 4 - Beta
Classifier: Intended Audience :: Science/Research
Classifier: Programming Language :: Python :: 3.6
Classifier: Programming Language :: Python :: 3.7
Classifier: Programming Language :: Python :: 3.8
Classifier: Topic :: Scientific/Engineering
Classifier: Topic :: Scientific/Engineering :: Artificial Intelligence
Classifier: Topic :: Software Development :: Libraries
Classifier: Topic :: Software Development :: Libraries :: Python Modules
Requires-Python: >=3.6
License-File: LICENSE
